koala_connectors/__init__.py
koala_connectors/connectors/__init__.py
koala_connectors/connectors/oracle_connector.py
tests/__init__.py
tests/test_oracle_connector.py
koala_connectors-0.0.5.dist-info/METADATA
koala_connectors-0.0.5.dist-info/WHEEL
koala_connectors-0.0.5.dist-info/top_level.txt
koala_connectors-0.0.5.dist-info/RECORD
